SungrowModbusClient/__init__.py
SungrowModbusClient/sungrow_register.py
sungrow_modbus_client-0.0.2.dist-info/LICENSE
sungrow_modbus_client-0.0.2.dist-info/METADATA
sungrow_modbus_client-0.0.2.dist-info/WHEEL
sungrow_modbus_client-0.0.2.dist-info/top_level.txt
sungrow_modbus_client-0.0.2.dist-info/RECORD
