Metadata-Version: 2.1
Name: sungrow-modbus-client
Version: 0.0.2
Summary: A Modbus client for sungrow solar inverter
Home-page: https://github.com/DasBasti/SungrowModbusClient
Author: Bastian Neumann
Author-email: neumann.bastian@gmail.com
License: UNKNOWN
Project-URL: Bug Tracker, https://github.com/DasBasti/SungrowModbusClient/issues
Platform: UNKNOWN
Classifier: Programming Language :: Python :: 3
Classifier: License :: OSI Approved :: MIT License
Classifier: Operating System :: OS Independent
Requires-Python: >=3.6
License-File: LICENSE
